webassets_cc
