Metadata-Version: 1.1
Name: webassets-compassconnector
Version: 0.2.1
Summary: Complete Compass integration for Webassets
Home-page: https://bitbucket.org/glorpen/webassets_compassconnector
Author: Arkadiusz Dzięgiel
Author-email: arkadiusz.dziegiel@glorpen.pl
License: GPL-3
Platform: UNKNOWN
Classifier: Development Status :: 5 - Production/Stable
Classifier: Intended Audience :: Developers
Classifier: License :: OSI Approved :: GNU General Public License v3 (GPLv3)
Classifier: Operating System :: OS Independent
Classifier: Programming Language :: Python
Classifier: Programming Language :: Python :: 3
Classifier: Topic :: Software Development :: Libraries
Classifier: Topic :: Internet :: WWW/HTTP
